setup.cfg
setup.py
fdscli/FDSShell.py
fdscli/__init__.py
fdscli.egg-info/PKG-INFO
fdscli.egg-info/SOURCES.txt
fdscli.egg-info/dependency_links.txt
fdscli.egg-info/entry_points.txt
fdscli.egg-info/requires.txt
fdscli.egg-info/top_level.txt
fdscli/functions/__init__.py
fdscli/functions/datetime_functions.py
fdscli/functions/volume/__init__.py
fdscli/functions/volume/snapshot_functions.py
fdscli/model/__init__.py
fdscli/model/base_model.py
fdscli/model/fds_error.py
fdscli/model/fds_id.py
fdscli/model/admin/__init__.py
fdscli/model/admin/role.py
fdscli/model/admin/tenant.py
fdscli/model/admin/user.py
fdscli/model/admin/connectors/__init__.py
fdscli/model/admin/connectors/active_directory.py
fdscli/model/admin/connectors/auth_engine.py
fdscli/model/admin/connectors/connector_domain_info.py
fdscli/model/admin/connectors/kerberoes_auth_engine.py
fdscli/model/common/__init__.py
fdscli/model/common/credential.py
fdscli/model/common/duration.py
fdscli/model/common/named_credential.py
fdscli/model/common/repository.py
fdscli/model/common/s3credentials.py
fdscli/model/common/size.py
fdscli/model/event/__init__.py
fdscli/model/event/event.py
fdscli/model/event/event_category.py
fdscli/model/event/event_descriptor.py
fdscli/model/event/event_severity.py
fdscli/model/event/event_source_info.py
fdscli/model/event/event_type.py
fdscli/model/health/__init__.py
fdscli/model/health/health_category.py
fdscli/model/health/health_record.py
fdscli/model/health/health_state.py
fdscli/model/health/system_health.py
fdscli/model/platform/__init__.py
fdscli/model/platform/address.py
fdscli/model/platform/domain.py
fdscli/model/platform/node.py
fdscli/model/platform/service.py
fdscli/model/platform/service_status.py
fdscli/model/statistics/__init__.py
fdscli/model/statistics/calculated.py
fdscli/model/statistics/context_def.py
fdscli/model/statistics/datapoint.py
fdscli/model/statistics/date_range.py
fdscli/model/statistics/firebreak_query_criteria.py
fdscli/model/statistics/metric_query_criteria.py
fdscli/model/statistics/metrics.py
fdscli/model/statistics/query_criteria.py
fdscli/model/statistics/series.py
fdscli/model/statistics/statistics.py
