Metadata-Version: 1.1
Name: fdscli
Version: 2.0.2
Summary: Formation CLI + SDK
Home-page: https://github.com/fds-dev/fds-cli
Author: Formation Data Systems
Author-email: support@formationds.com
License: MIT
Keywords: Formation Data Systems CLI SDK
Platform: UNKNOWN
Classifier: Development Status :: 4 - Beta
Classifier: Intended Audience :: Developers
Classifier: Intended Audience :: System Administrators
Classifier: Topic :: Software Development :: Build Tools
Classifier: License :: OSI Approved :: MIT License
Classifier: Programming Language :: Python :: 2
Classifier: Programming Language :: Python :: 2.7
